phdoc/__init__.py
phdoc/builder.py
phdoc/cache.py
phdoc/config.py
phdoc/directories.py
phdoc/exc.py
phdoc/mdx_fold.py
phdoc/mdx_mathjax.py
phdoc/render.py
phdoc/server.py
phdoc/templates.py
phdoc/wsgi.py
phdoc/cli/__init__.py
phdoc/cli/commands.py
phdoc/cli/main.py
phdoc/cli/parser.py
phdoc/static/default-static/media/css/basic.css
phdoc/static/default-static/media/css/elements.css
phdoc/static/default-static/media/css/pygments.css
phdoc/static/default-static/media/js/addcss.js
phdoc/static/default-static/media/js/fold.js
phdoc/static/default-static/media/js/hyphenator.js
phdoc/static/default-templates/404.html
phdoc/static/default-templates/base.html
phdoc/static/default-templates/document.html
phdoc/static/default-templates/listing.html
phdoc/static/default-templates/default/404.html
phdoc/static/default-templates/default/base.html
phdoc/static/default-templates/default/document.html
phdoc/static/default-templates/default/listing.html
phdoc/static/default-templates/macros/crumbs
phdoc/static/default-templates/macros/html
phdoc-0.7.4.dist-info/DESCRIPTION.rst
phdoc-0.7.4.dist-info/METADATA
phdoc-0.7.4.dist-info/RECORD
phdoc-0.7.4.dist-info/WHEEL
phdoc-0.7.4.dist-info/entry_points.txt
phdoc-0.7.4.dist-info/metadata.json
phdoc-0.7.4.dist-info/top_level.txt
