Metadata-Version: 2.0
Name: phdoc
Version: 0.7.4
Summary: A Markdown-based wiki crafted for academics.
Home-page: http://github.com/lrem/phdoc
Author: Remigiusz 'lRem' Modrzejewski
Author-email: UNKNOWN
License: UNKNOWN
Platform: UNKNOWN
